roblox_speed_api/.gitignore
roblox_speed_api/__init__.py
roblox_speed_api/_cache.py
roblox_speed_api/client.py
roblox_speed_api/exceptions.py
roblox_speed_api/facade.py
roblox_speed_api/test_smoke.py
roblox_speed_api-0.2.1.dist-info/METADATA
roblox_speed_api-0.2.1.dist-info/WHEEL
roblox_speed_api-0.2.1.dist-info/RECORD
